pylibpcap3/__init__.py
pylibpcap3/aiosession.py
pylibpcap3/mplistener.py
pylibpcap3/mpsession.py
pylibpcap3/pcap_server.py
pylibpcap3/defs/__init__.py
pylibpcap3/defs/functions.py
pylibpcap3/defs/structs.py
pylibpcap3/utils/__init__.py
pylibpcap3/utils/aqueue.py
pylibpcap3-0.0.3.dist-info/LICENSE
pylibpcap3-0.0.3.dist-info/METADATA
pylibpcap3-0.0.3.dist-info/WHEEL
pylibpcap3-0.0.3.dist-info/top_level.txt
pylibpcap3-0.0.3.dist-info/zip-safe
pylibpcap3-0.0.3.dist-info/RECORD
